README.rst
setup.cfg
setup.py
webobtoolkit/__init__.py
webobtoolkit/client.py
webobtoolkit/constants.py
webobtoolkit/filters.py
webobtoolkit/log.py
webobtoolkit/testing.py
webobtoolkit.egg-info/PKG-INFO
webobtoolkit.egg-info/SOURCES.txt
webobtoolkit.egg-info/dependency_links.txt
webobtoolkit.egg-info/entry_points.txt
webobtoolkit.egg-info/not-zip-safe
webobtoolkit.egg-info/requires.txt
webobtoolkit.egg-info/top_level.txt