Metadata-Version: 1.1
Name: webobtoolkit
Version: 0.2.3
Summary: UNKNOWN
Home-page: https://github.com/twillis/webobtoolkit
Author: Tom Willis
Author-email: tom.willis@gmail.com
License: UNKNOWN
Keywords: webob HTTP client
Platform: UNKNOWN
Classifier: Environment :: Web Environment
Classifier: Development Status :: 4 - Beta
Classifier: Intended Audience :: Developers
Classifier: License :: Public Domain
Classifier: Programming Language :: Python
Classifier: Programming Language :: Python :: 3
